lob_api_sdk-1.0.0.dist-info/licenses/LICENSE
lobapi/__init__.py
lobapi/api_helper.py
lobapi/configuration.py
lobapi/lobapi_client.py
lobapi/controllers/__init__.py
lobapi/controllers/address_verification_intl_controller.py
lobapi/controllers/address_verification_us_controller.py
lobapi/controllers/addresses_controller.py
lobapi/controllers/bank_accounts_controller.py
lobapi/controllers/base_controller.py
lobapi/controllers/billing_groups_controller.py
lobapi/controllers/campaign_creatives_controller.py
lobapi/controllers/campaign_uploads_controller.py
lobapi/controllers/campaigns_controller.py
lobapi/controllers/card_orders_controller.py
lobapi/controllers/cards_controller.py
lobapi/controllers/checks_controller.py
lobapi/controllers/letters_controller.py
lobapi/controllers/postcards_controller.py
lobapi/controllers/reverse_geocode_controller.py
lobapi/controllers/self_mailers_controller.py
lobapi/controllers/template_versions_controller.py
lobapi/controllers/templates_controller.py
lobapi/controllers/zipcode_controller.py
lobapi/exceptions/__init__.py
lobapi/exceptions/api_exception.py
lobapi/exceptions/error_exception.py
lobapi/exceptions/validation_error_exception.py
lobapi/http/__init__.py
lobapi/http/http_call_back.py
lobapi/http/http_method_enum.py
lobapi/http/http_request.py
lobapi/http/http_response.py
lobapi/http/auth/__init__.py
lobapi/http/auth/basic_auth.py
lobapi/models/__init__.py
lobapi/models/a_dictionary_with_a_data_property_that_contains_an_array_of_up_to_limit_addresses_each_entry_in_the_array_is_a_separate_address_object_the_previous_and_next_page_of_address_entries_can_be_retrieved_by_calling_the_endpoint_contained_in_the_previous_ur.py
lobapi/models/a_dictionary_with_a_data_property_that_contains_an_array_of_up_to_limit_bank_accounts_each_entry_in_the_array_is_a_separate_bank_account_the_previous_and_next_page_of_bank_accounts_can_be_retrieved_by_calling_the_endpoint_contained_in_the_previous_ur.py
lob_api_sdk-1.0.0.dist-info/METADATA
lob_api_sdk-1.0.0.dist-info/WHEEL
lob_api_sdk-1.0.0.dist-info/top_level.txt
lob_api_sdk-1.0.0.dist-info/RECORD
