Metadata-Version: 2.4
Name: lob-api-sdk
Version: 1.0.0
Summary: The Lob API is a comprehensive direct mail and address verification service that helps developers extend their applications into the physical world through automated print and mail capabilities. It provides APIs for creating and managing addresses, verifying US and international addresses, managing bank accounts for check printing, and handling campaigns for bulk mail operations.
Author-email: Muhammad Hamza Shahzad <muhammad.hamza@apimatic.io>
Project-URL: Documentation, https://docs.apimatic.io/
Requires-Python: >=3.7
License-File: LICENSE
Requires-Dist: apimatic-core>=0.2.20,~=0.2.0
Requires-Dist: apimatic-core-interfaces>=0.1.5,~=0.1.0
Requires-Dist: apimatic-requests-client-adapter>=0.1.6,~=0.1.0
Provides-Extra: testutils
Requires-Dist: pytest>=7.2.2; extra == "testutils"
Dynamic: license-file
